{
  "_comment": "This data is an early work-in-progress and contains errors. Keys with _else are produced with non-trained Stanford NLP and as such only includes capitalized words. The + designates a segment range. Produced by @michaelh at Discuss and Discover SuttaCentral forum - please get in touch! Finished code forthcoming.",
  "an8.24:1.3+an8.24:1.4^who_else_mentioned": "Hatthaka",
  "an8.24:1.5+an8.24:1.15^who_else_mentioned": "Buddha",
  "an8.24:1.16+an8.24:1.18^who_else_mentioned": "Hatthaka",
  "an8.24:2.3+an8.24:2.13^who_else_mentioned": "Hatthaka of \u0100\u1e37av\u012b",
  "an8.24:1.3+an8.24:1.4": "the Buddha",
  "an8.24:1.5+an8.24:1.15": "Hatthaka of \u0100\u1e37av\u012b",
  "an8.24:1.16+an8.24:1.18": "the Buddha",
  "an8.24:2.3+an8.24:2.13": "the Buddha",
  "before^an8.24:2.3^who_around": "Hatthaka of \u0100\u1e37av\u012b, five hundred lay followers",
  "before^an8.24:2.3^where": "\u0100\u1e37av\u012b, at the Agg\u0101\u1e37ava Tree-shrine",
  "where": "\u0100\u1e37av\u012b, at the Agg\u0101\u1e37ava Tree-shrine"
}