{
  "_comment": "This data is an early work-in-progress and contains errors. Keys with _else are produced with non-trained Stanford NLP and as such only includes capitalized words. The + designates a segment range. Produced by @michaelh at Discuss and Discover SuttaCentral forum - please get in touch! Finished code forthcoming.",
  "sn11.1:1.4^speaker": "the Buddha",
  "sn11.1:1.5^speaker": "The mendicants",
  "sn11.1:2.1+sn11.1:8.2^speaker": "the Buddha",
  "sn11.1:2.1+sn11.1:8.2^who_else_mentioned": [
    "Sakka",
    "Suvīra"
  ],
  "sn11.1:2.1^event_dppn_headwords_before_or_around_this_segment": [
    "Jetavana"
  ],
  "sn11.1:2.1^where_before_or_around_this_segment": [
    "Jeta's Grove Anāthapiṇḍika's monastery near Sāvatthī"
  ],
  "sn11.1:2.1^who_present_before_or_around_this_segment": [
    "The mendicants"
  ],
  "sn11.1:2.1^who_mentioned_before_or_around_this_segment": [
    "The demons",
    "the gods"
  ],
  "sn11.1^initial_location_dppn_headword": [
    "Jetavana"
  ],
  "sn11.1^where": "Jeta's Grove, Anāthapiṇḍika's monastery near Sāvatthī"
}