{
  "_comment": "This data is an early work-in-progress and contains errors. Keys with _else are produced with non-trained Stanford NLP and as such only includes capitalized words. The + designates a segment range. Produced by @michaelh at Discuss and Discover SuttaCentral forum - please get in touch! Finished code forthcoming.",
  "sn6.3:2.2^speaker": "Brahmadeva",
  "sn6.3:3.5+sn6.3:3.6^speaker": "Brahmā Sahampati",
  "sn6.3:3.5+sn6.3:3.6^who_else_mentioned": [
    "Brahmadeva"
  ],
  "sn6.3:4.1+sn6.3:9.4^speaker": "Brahmā Sahampati",
  "sn6.3:4.1+sn6.3:9.4^where_else_mentioned": [
    "Brahmā",
    "Brahmadeva"
  ],
  "sn6.3:4.1^geographic_locations_here_and_before": [
    "Sāvatthī",
    "Jetavana"
  ],
  "sn6.3:4.1^where_here_and_before": [
    "Sāvatthī in Jeta's Grove",
    "Anāthapiṇḍika's monastery"
  ],
  "sn6.3:4.1^who_around_here_and_before": [
    "Brahmadeva's mother",
    "the brahmin lady"
  ],
  "sn6.3:4.1^who_mentioned_here_and_before": [
    "Brahmā"
  ],
  "sn6.3^initial_geographic_location": [
    "Sāvatthī",
    "Jetavana"
  ],
  "sn6.3^where": "Sāvatthī in Jeta's Grove, Anāthapiṇḍika's monastery"
}