{
  "_comment": "This data is an early work-in-progress and contains errors. Keys with _else are produced with non-trained Stanford NLP and as such only includes capitalized words. The + designates a segment range. Produced by @michaelh at Discuss and Discover SuttaCentral forum - please get in touch! Finished code forthcoming.",
  "dn16:1.1.5^speaker": "King Ajātasattu Vedehiputta of Māgadha",
  "dn16:1.1.5^who_else_mentioned": [
    "Vajjis"
  ],
  "dn16:1.2.2+dn16:1.2.9^speaker": "Vassakāra the brahmin minister of Māgadha",
  "dn16:1.2.2+dn16:1.2.9^where_else_mentioned": [
    "Māgadha"
  ],
  "dn16:1.2.2+dn16:1.2.9^who_else_mentioned": [
    "Ajātasattu Vedehiputta",
    "Vajjis",
    "Buddha"
  ],
  "dn16:1.2.7^speaker": "King Ajātasattu Vedehiputta of Māgadha",
  "dn16:1.2.7^who_else_mentioned": [
    "Vajjis"
  ],
  "dn16:1.3.1^speaker": "Vassakāra the brahmin minister of Māgadha",
  "dn16:1.3.4+dn16:1.3.7^speaker": "Vassakāra the brahmin minister of Māgadha",
  "dn16:1.3.4+dn16:1.3.7^where_else_mentioned": [
    "Māgadha"
  ],
  "dn16:1.3.4+dn16:1.3.7^who_else_mentioned": [
    "Gotama",
    "Ajātasattu Vedehiputta",
    "Ajātasattu",
    "Vajjis"
  ],
  "dn16:1.4.3^speaker": "the Buddha",
  "dn16:1.4.3^who_else_mentioned": [
    "Vajjis"
  ],
  "dn16:1.4.4^speaker": "Ānanda",
  "dn16:1.4.5+dn16:1.4.6^speaker": "the Buddha",
  "dn16:1.4.5+dn16:1.4.6^who_else_mentioned": [
    "Vajjis"
  ],
  "dn16:1.4.7^speaker": "Ānanda",
  "dn16:1.4.8+dn16:1.4.9^speaker": "the Buddha",
  "dn16:1.4.8+dn16:1.4.9^who_else_mentioned": [
    "Vajjis",
    "Vajjian"
  ],
  "dn16:1.4.10^speaker": "Ānanda",
  "dn16:1.4.11+dn16:1.4.12^speaker": "the Buddha",
  "dn16:1.4.11+dn16:1.4.12^who_else_mentioned": [
    "Vajjis",
    "Vajjian"
  ],
  "dn16:1.4.13^speaker": "Ānanda",
  "dn16:1.4.14+dn16:1.4.15^speaker": "the Buddha",
  "dn16:1.4.14+dn16:1.4.15^who_else_mentioned": [
    "Vajjis",
    "Vajjian"
  ],
  "dn16:1.4.16^speaker": "Ānanda",
  "dn16:1.4.17+dn16:1.4.18^speaker": "the Buddha",
  "dn16:1.4.17+dn16:1.4.18^who_else_mentioned": [
    "Vajjis",
    "Vajjian"
  ],
  "dn16:1.4.19^geographic_locations_here_and_before": [
    "Rājagaha",
    "Gijjhakūṭa"
  ],
  "dn16:1.4.19^speaker": "Ānanda",
  "dn16:1.4.19^where_here_and_before": [
    "Rājagaha",
    "on the Vulture's Peak Mountain"
  ],
  "dn16:1.4.19^who_around_here_and_before": [
    "Vassakāra the brahmin minister of Māgadha",
    "King Ajātasattu Vedehiputta of Māgadha"
  ],
  "dn16:1.4.19^who_mentioned_here_and_before": [
    "Vajjis"
  ],
  "dn16:1.4.20+dn16:1.4.21^speaker": "the Buddha",
  "dn16:1.4.20+dn16:1.4.21^who_else_mentioned": [
    "Vajjis",
    "Vajjian"
  ],
  "dn16:1.4.22^speaker": "Ānanda",
  "dn16:1.4.23^speaker": "the Buddha",
  "dn16:1.4.23^where_else_mentioned": [
    "Vajjis"
  ],
  "dn16:1.5.2+dn16:1.5.4^speaker": "the Buddha",
  "dn16:1.5.2+dn16:1.5.4^where_else_mentioned": [
    "Vesālī",
    "Sārandada"
  ],
  "dn16:1.5.2+dn16:1.5.4^who_else_mentioned": [
    "Vajjis"
  ],
  "dn16:1.5.6+dn16:1.5.9^speaker": "Vassakāra the brahmin",
  "dn16:1.5.6+dn16:1.5.9^who_else_mentioned": [
    "Gotama",
    "Vajjis",
    "King Ajātasattu"
  ],
  "dn16:1.5.10^speaker": "the Buddha",
  "dn16:1.6.2^speaker": "the Buddha",
  "dn16:1.6.2^where_else_mentioned": [
    "Rājagaha"
  ],
  "dn16:1.6.2^who_else_mentioned": [
    "Ānanda"
  ],
  "dn16:1.6.3^speaker": "Ānanda",
  "dn16:1.6.4^speaker": "Ānanda",
  "dn16:1.6.4^who_else_mentioned": [
    "Saṅgha"
  ],
  "dn16:1.6.7+dn16:1.6.8^speaker": "the Buddha",
  "dn16:1.6.9^geographic_locations_here_and_before": [
    "Vesāli"
  ],
  "dn16:1.6.9^speaker": "the mendicants",
  "dn16:1.6.9^where_here_and_before": [
    "Vesālī at the Sārandada woodland shrine"
  ],
  "dn16:1.6.9^who_around_here_and_before": [
    "Vassakāra the brahmin"
  ],
  "dn16:1.6.11+dn16:1.11.10^speaker": "the Buddha",
  "dn16:1.6.11+dn16:1.11.10^who_else_mentioned": [
    "Saṅgha"
  ],
  "dn16:1.12.2+dn16:1.12.6^speaker": "the Buddha",
  "dn16:1.13.2^speaker": "the Buddha",
  "dn16:1.13.2^who_else_mentioned": [
    "Ānanda"
  ],
  "dn16:1.13.3^speaker": "Ānanda",
  "dn16:1.14.3+dn16:1.14.7^speaker": "the Buddha",
  "dn16:1.15.2^speaker": "the Buddha",
  "dn16:1.15.2^who_else_mentioned": [
    "Ānanda"
  ],
  "dn16:1.15.3^speaker": "Ānanda",
  "dn16:1.16.2+dn16:1.16.3^speaker": "Sāriputta",
  "dn16:1.16.2+dn16:1.16.3^who_else_mentioned": [
    "Buddha"
  ],
  "dn16:1.16.4+dn16:1.16.8^speaker": "the Buddha",
  "dn16:1.16.4+dn16:1.16.8^who_else_mentioned": [
    "Sāriputta",
    "Buddha",
    "Buddhas"
  ],
  "dn16:1.16.9^speaker": "Sāriputta",
  "dn16:1.16.10+dn16:1.16.11^speaker": "the Buddha",
  "dn16:1.16.10+dn16:1.16.11^who_else_mentioned": [
    "Buddhas"
  ],
  "dn16:1.16.12^speaker": "Sāriputta",
  "dn16:1.16.13+dn16:1.16.14^speaker": "the Buddha",
  "dn16:1.16.13+dn16:1.16.14^who_else_mentioned": [
    "Buddha"
  ],
  "dn16:1.16.15^speaker": "Sāriputta",
  "dn16:1.16.16+dn16:1.16.17^speaker": "the Buddha",
  "dn16:1.16.16+dn16:1.16.17^who_else_mentioned": [
    "Sāriputta",
    "Buddhas"
  ],
  "dn16:1.17.1+dn16:1.17.9^speaker": "Sāriputta",
  "dn16:1.17.1+dn16:1.17.9^who_else_mentioned": [
    "Buddhas"
  ],
  "dn16:1.18.2+dn16:1.18.6^speaker": "the Buddha",
  "dn16:1.19.2^speaker": "the Buddha",
  "dn16:1.19.2^where_else_mentioned": [
    "Pāṭali Village"
  ],
  "dn16:1.19.2^who_else_mentioned": [
    "Ānanda"
  ],
  "dn16:1.19.3^speaker": "Ānanda",
  "dn16:1.20.3^geographic_locations_here_and_before": [
    "Gijjhakūṭa",
    "Rājagaha",
    "Ambalaṭṭhikā",
    "Nāḷandā"
  ],
  "dn16:1.20.3^speaker": "the lay followers of Pāṭali Village",
  "dn16:1.20.3^where_here_and_before": [
    "Vulture's Peak",
    "Rājagaha",
    "Ambalaṭṭhikā",
    "Nāḷandā",
    "Pāṭali Village"
  ],
  "dn16:1.20.3^who_around_here_and_before": [
    "Ānanda",
    "Sāriputta"
  ],
  "dn16:1.20.3^who_mentioned_here_and_before": [
    ""
  ],
  "dn16:1.21.3^speaker": "the lay followers of Pāṭali Village",
  "dn16:1.23.2+dn16:1.24.13^speaker": "the Buddha",
  "dn16:1.25.2^speaker": "the Buddha",
  "dn16:1.25.3^speaker": "the lay followers of Pāṭali Village",
  "dn16:1.27.5^speaker": "the Buddha",
  "dn16:1.27.5^who_else_mentioned": [
    "Ānanda"
  ],
  "dn16:1.27.6^speaker": "Ānanda",
  "dn16:1.27.6^who_else_mentioned": [
    "Magadhan",
    "Sunidha",
    "Vassakāra",
    "Vajjis"
  ],
  "dn16:1.28.1+dn16:1.28.9^speaker": "the Buddha",
  "dn16:1.28.1+dn16:1.28.9^where_else_mentioned": [
    "Pāṭaliputta"
  ],
  "dn16:1.29.3^speaker": "Sunidha and Vassakāra",
  "dn16:1.29.3^who_else_mentioned": [
    "Gotama",
    "Saṅgha"
  ],
  "dn16:1.30.2^speaker": "Sunidha and Vassakāra",
  "dn16:1.30.2^who_else_mentioned": [
    "Gotama"
  ],
  "dn16:1.31.2+dn16:1.31.13^speaker": "the Buddha",
  "dn16:1.32.2+dn16:1.32.3^speaker": "Sunidha and Vassakāra",
  "dn16:1.32.2+dn16:1.32.3^where_else_mentioned": [
    "the Ganges River"
  ],
  "dn16:1.32.2+dn16:1.32.3^who_else_mentioned": [
    "Gotama"
  ],
  "dn16:1.32.2^where_here_and_before": [
    "Pāṭali Village"
  ],
  "dn16:1.32.2^who_around_here_and_before": [
    "the Saṅgha of mendicants",
    "Ānanda"
  ],
  "dn16:1.32.2^who_mentioned_here_and_before": [
    "Vajjis",
    "gods of the Thirty-Three"
  ],
  "dn16:1.34.3+dn16:1.34.6^speaker": "the Buddha",
  "dn16:2.1.2^speaker": "the Buddha",
  "dn16:2.1.2^where_else_mentioned": [
    "Koṭigāma"
  ],
  "dn16:2.1.2^who_else_mentioned": [
    "Ānanda"
  ],
  "dn16:2.1.3^speaker": "Ānanda",
  "dn16:2.2.2+dn16:2.2.8^speaker": "the Buddha",
  "dn16:2.3.3+dn16:2.3.10^speaker": "the Buddha",
  "dn16:2.4.2+dn16:2.4.6^speaker": "the Buddha",
  "dn16:2.5.2^speaker": "the Buddha",
  "dn16:2.5.2^who_else_mentioned": [
    "Ānanda"
  ],
  "dn16:2.5.3^speaker": "Ānanda",
  "dn16:2.6.2+dn16:2.6.13^speaker": "Ānanda",
  "dn16:2.6.2+dn16:2.6.13^where_else_mentioned": [
    "Nādika",
    "Nikata",
    "Kaṭissaha",
    "Tuṭṭha",
    "Santuṭṭha",
    "Bhadda"
  ],
  "dn16:2.6.2+dn16:2.6.13^who_else_mentioned": [
    "Sāḷha",
    "Nandā",
    "Sudatta",
    "Sujātā",
    "Kakkaṭa",
    "Kaḷibha",
    "Subhadda"
  ],
  "dn16:2.7.1+dn16:2.9.10^speaker": "the Buddha",
  "dn16:2.7.1+dn16:2.9.10^where_else_mentioned": [
    "Kaḷibha",
    "Nikata",
    "Kaṭissaha",
    "Tuṭṭha",
    "Santuṭṭha",
    "Bhadda",
    "Nādika"
  ],
  "dn16:2.7.1+dn16:2.9.10^who_else_mentioned": [
    "Sāḷha",
    "Nandā",
    "Sudatta",
    "Sujātā",
    "Kakkaṭa",
    "Subhadda",
    "Ānanda",
    "Buddha",
    "Saṅgha"
  ],
  "dn16:2.10.2+dn16:2.10.6^speaker": "the Buddha",
  "dn16:2.11.2^speaker": "the Buddha",
  "dn16:2.11.2^who_else_mentioned": [
    "Ānanda"
  ],
  "dn16:2.11.3^geographic_locations_here_and_before": [
    "Jetavana",
    "Koṭigāma",
    "Vesāli"
  ],
  "dn16:2.11.3^speaker": "Ānanda",
  "dn16:2.11.3^where_here_and_before": [
    "Jeta's Grove",
    "Ganges River",
    "Koṭigāma",
    "Nādika",
    "Vesālī",
    "Ambapālī's mango grove"
  ],
  "dn16:2.11.3^who_around_here_and_before": [
    "Sunidha",
    "Vassakāra",
    "Saṅgha of mendicants"
  ],
  "dn16:2.11.3^who_mentioned_here_and_before": [
    "Sāḷha",
    "Subhadda"
  ],
  "dn16:2.12.2+dn16:2.13.5^speaker": "the mendicants",
  "dn16:2.14.6^speaker": "the Buddha",
  "dn16:2.14.6^who_else_mentioned": [
    "Buddha",
    "Saṅgha"
  ],
  "dn16:2.16.3^speaker": "the Licchavis of Vesālī",
  "dn16:2.16.4^speaker": "Ambapālī the courtesan",
  "dn16:2.16.4^who_else_mentioned": [
    "Buddha",
    "Saṅgha"
  ],
  "dn16:2.16.5^speaker": "the Licchavis of Vesālī",
  "dn16:2.16.6^speaker": "Ambapālī the courtesan",
  "dn16:2.16.6^who_else_mentioned": [
    "Vesālī"
  ],
  "dn16:2.16.8^speaker": "the Licchavis of Vesālī",
  "dn16:2.17.3+dn16:2.17.6^speaker": "the Buddha",
  "dn16:2.17.3+dn16:2.17.6^who_else_mentioned": [
    "Licchavis"
  ],
  "dn16:2.18.4^speaker": "the Licchavis of Vesālī",
  "dn16:2.18.4^who_else_mentioned": [
    "Buddha",
    "Saṅgha"
  ],
  "dn16:2.18.6^speaker": "the Buddha",
  "dn16:2.18.8^speaker": "the Licchavis of Vesālī",
  "dn16:2.19.2^speaker": "Ambapālī the courtesan",
  "dn16:2.19.7^geographic_locations_here_and_before": [
    "Vesāli"
  ],
  "dn16:2.19.7^speaker": "Ambapālī the courtesan",
  "dn16:2.19.7^where_here_and_before": [
    "Vesālī",
    "Ambapālī's mango grove"
  ],
  "dn16:2.19.7^who_around_here_and_before": [
    "Ānanda",
    "the mendicant Saṅgha",
    "the Licchavis of Vesālī"
  ],
  "dn16:2.19.7^who_else_mentioned": [
    "Saṅgha",
    "Buddha"
  ],
  "dn16:2.19.7^who_mentioned_here_and_before": [
    "the gods of the Thirty-Three"
  ],
  "dn16:2.20.2+dn16:2.20.6^speaker": "the Buddha",
  "dn16:2.21.2^speaker": "the Buddha",
  "dn16:2.21.2^where_else_mentioned": [
    "Beluva"
  ],
  "dn16:2.21.2^who_else_mentioned": [
    "Ānanda"
  ],
  "dn16:2.21.3^speaker": "Ānanda",
  "dn16:2.22.2+dn16:2.22.3^speaker": "the Buddha",
  "dn16:2.22.2+dn16:2.22.3^where_else_mentioned": [
    "Beluva"
  ],
  "dn16:2.22.2+dn16:2.22.3^who_else_mentioned": [
    "Vesālī"
  ],
  "dn16:2.22.4^speaker": "the mendicants",
  "dn16:2.23.4+dn16:2.23.5^speaker": "the Buddha",
  "dn16:2.23.4+dn16:2.23.5^who_else_mentioned": [
    "Saṅgha"
  ],
  "dn16:2.24.5+dn16:2.24.8^speaker": "Ānanda",
  "dn16:2.24.5+dn16:2.24.8^who_else_mentioned": [
    "Buddha",
    "Saṅgha"
  ],
  "dn16:2.25.1+dn16:2.26.8^speaker": "the Buddha",
  "dn16:2.25.1+dn16:2.26.8^who_else_mentioned": [
    "Saṅgha",
    "Ānanda",
    "The Realized One"
  ],
  "dn16:3.1.3+dn16:3.1.4^speaker": "the Buddha",
  "dn16:3.1.5^speaker": "Ānanda",
  "dn16:3.2.4+dn16:3.3.2^speaker": "the Buddha",
  "dn16:3.2.4+dn16:3.3.2^where_else_mentioned": [
    "Gotamaka",
    "Sattamba",
    "Bahuputta",
    "Sārandada"
  ],
  "dn16:3.2.4+dn16:3.3.2^who_else_mentioned": [
    "Vesālī",
    "Udena",
    "Cāpāla"
  ],
  "dn16:3.2.4^geographic_locations_here_and_before": [
    "Vesāli",
    "Beluva"
  ],
  "dn16:3.2.4^where_here_and_before": [
    "Ambapālī's grove",
    "Vesālī",
    "the little village of Beluva",
    "the Cāpāla shrine"
  ],
  "dn16:3.2.4^who_around_here_and_before": [
    "the mendicant Saṅgha",
    "Ānanda"
  ],
  "dn16:3.2.4^who_mentioned_here_and_before": [
    "Māra"
  ],
  "dn16:3.4.3^speaker": "Ānanda",
  "dn16:3.4.3^who_else_mentioned": [
    "the Blessed One"
  ],
  "dn16:3.5.3+dn16:3.5.5^speaker": "the Buddha",
  "dn16:3.5.3+dn16:3.5.5^where_else_mentioned": [
    "Gotamaka",
    "Sattamba",
    "Bahuputta",
    "Sārandada"
  ],
  "dn16:3.5.3+dn16:3.5.5^who_else_mentioned": [
    "Vesālī",
    "Udena",
    "Cāpāla"
  ],
  "dn16:3.5.8^speaker": "Ānanda",
  "dn16:3.5.8^who_else_mentioned": [
    "the Blessed One"
  ],
  "dn16:3.6.2+dn16:3.6.3^speaker": "the Buddha",
  "dn16:3.6.4^speaker": "Ānanda",
  "dn16:3.7.2+dn16:3.8.18^speaker": "Māra the Wicked",
  "dn16:3.7.2+dn16:3.8.18^where_else_mentioned": [
    "the Holy One"
  ],
  "dn16:3.7.2+dn16:3.8.18^who_else_mentioned": [
    "the Blessed One",
    "Buddha"
  ],
  "dn16:3.9.2+dn16:3.9.3^speaker": "the Buddha",
  "dn16:3.9.2+dn16:3.9.3^who_else_mentioned": [
    "Wicked One"
  ],
  "dn16:3.10.4+dn16:3.10.7^speaker": "the Buddha",
  "dn16:3.11.2+dn16:3.11.4^speaker": "Ānanda",
  "dn16:3.12.4+dn16:3.12.7^speaker": "Ānanda",
  "dn16:3.13.1+dn16:3.37.4^speaker": "the Buddha",
  "dn16:3.13.1+dn16:3.37.4^where_else_mentioned": [
    "Uruvelā",
    "the Nerañjarā River",
    "the Holy One"
  ],
  "dn16:3.13.1+dn16:3.37.4^who_else_mentioned": [
    "Joyful Gods",
    "Māra",
    "the Blessed One",
    "Buddha",
    "Wicked One",
    "Cāpāla"
  ],
  "dn16:3.38.2^speaker": "Ānanda",
  "dn16:3.38.2^who_else_mentioned": [
    "the Blessed One"
  ],
  "dn16:3.38.3+dn16:3.38.4^speaker": "the Buddha",
  "dn16:3.38.3+dn16:3.38.4^who_else_mentioned": [
    "Ānanda"
  ],
  "dn16:3.39.3^speaker": "Ānanda",
  "dn16:3.39.3^who_else_mentioned": [
    "the Blessed One"
  ],
  "dn16:3.39.4^speaker": "the Buddha",
  "dn16:3.39.5^speaker": "Ānanda",
  "dn16:3.39.6^speaker": "the Buddha",
  "dn16:3.39.6^where_here_and_before": [
    "Cāpāla tree shrine"
  ],
  "dn16:3.39.6^who_around_here_and_before": [
    "Māra the Wicked"
  ],
  "dn16:3.39.6^who_mentioned_here_and_before": [
    "Vesālī",
    "Udena",
    "Buddhaka",
    "Sattamba",
    "Bahuputta",
    "Sārandada",
    "and Cāpāla"
  ],
  "dn16:3.40.1+dn16:3.40.3^speaker": "Ānanda",
  "dn16:3.40.1+dn16:3.40.3^who_else_mentioned": [
    "Buddha"
  ],
  "dn16:3.40.4^speaker": "the Buddha",
  "dn16:3.40.5^speaker": "Ānanda",
  "dn16:3.40.6+dn16:3.48.8^speaker": "the Buddha",
  "dn16:3.40.6+dn16:3.48.8^where_else_mentioned": [
    "Rājagaha",
    "the Vulture’s Peak Mountain",
    "the Gotama banyan",
    "the Sattapaṇṇi cave",
    "Vebhara",
    "the Black rock",
    "Isigili",
    "the Cool Grove",
    "Jīvaka",
    "the Maddakucchi deer",
    "Vesālī",
    "Gotamaka",
    "Sattamba",
    "Bahuputta",
    "Sārandada"
  ],
  "dn16:3.40.6+dn16:3.48.8^who_else_mentioned": [
    "Ānanda",
    "Udena",
    "The Realized One"
  ],
  "dn16:3.48.9^speaker": "Ānanda",
  "dn16:3.49.2^speaker": "the Buddha",
  "dn16:3.49.2^where_else_mentioned": [
    "Vesālī"
  ],
  "dn16:3.49.2^who_else_mentioned": [
    "Ānanda"
  ],
  "dn16:3.49.3^speaker": "Ānanda",
  "dn16:3.49.4^speaker": "Ānanda",
  "dn16:3.49.4^who_else_mentioned": [
    "Saṅgha"
  ],
  "dn16:3.50.3+dn16:3.51.1^speaker": "the Buddha",
  "dn16:3.51.3+dn16:3.51.6^speaker": "the Buddha",
  "dn16:3.51.9+dn16:3.51.20^speaker": "the Buddha",
  "dn16:4.1.3+dn16:4.1.4^speaker": "the Buddha",
  "dn16:4.1.3+dn16:4.1.4^where_else_mentioned": [
    "Bhaṇḍagāma"
  ],
  "dn16:4.1.3+dn16:4.1.4^who_else_mentioned": [
    "Vesālī",
    "Ānanda"
  ],
  "dn16:4.1.5^speaker": "Ānanda",
  "dn16:4.2.4+dn16:4.2.10^speaker": "the Buddha",
  "dn16:4.3.3+dn16:4.3.10^speaker": "the Buddha",
  "dn16:4.3.3+dn16:4.3.10^who_else_mentioned": [
    "Gotama",
    "Buddha"
  ],
  "dn16:4.4.2+dn16:4.4.6^speaker": "the Buddha",
  "dn16:4.5.2^speaker": "the Buddha",
  "dn16:4.5.2^who_else_mentioned": [
    "Ānanda"
  ],
  "dn16:4.5.3^speaker": "the Buddha",
  "dn16:4.5.3^where_else_mentioned": [
    "Ambagāma"
  ],
  "dn16:4.5.4^speaker": "the Buddha",
  "dn16:4.5.4^where_else_mentioned": [
    "Jambugāma"
  ],
  "dn16:4.5.5^speaker": "the Buddha",
  "dn16:4.5.5^where_else_mentioned": [
    "Bhoganagara"
  ],
  "dn16:4.6.1^speaker": "Ānanda",
  "dn16:4.7.3+dn16:4.7.4^speaker": "the Buddha",
  "dn16:4.7.5^geographic_locations_here_and_before": [
    "Jetavana",
    "Vesāli",
    "Bhaṇḍagāma",
    "Ambagāma",
    "Jambugāma",
    "Bhoganagara"
  ],
  "dn16:4.7.5^speaker": "the mendicants",
  "dn16:4.7.5^where_here_and_before": [
    "Jeta's Grove",
    "Vesālī",
    "Bhaṇḍagāma",
    "Hatthigāma",
    "Ambagāma",
    "Jambugāma",
    "Bhoganagara",
    "Ānanda shrine"
  ],
  "dn16:4.7.5^who_around_here_and_before": [
    "a large Saṅgha of mendicants"
  ],
  "dn16:4.7.5^who_mentioned_here_and_before": [
    ""
  ],
  "dn16:4.8.1+dn16:4.11.15^speaker": "the mendicant",
  "dn16:4.8.1+dn16:4.11.15^who_else_mentioned": [
    "Buddha",
    "Saṅgha"
  ],
  "dn16:4.12.2+dn16:4.12.6^speaker": "the Buddha",
  "dn16:4.13.2^speaker": "the Buddha",
  "dn16:4.13.2^who_else_mentioned": [
    "Ānanda"
  ],
  "dn16:4.13.3^speaker": "Ānanda",
  "dn16:4.15.1^speaker": "Cunda",
  "dn16:4.15.1^who_else_mentioned": [
    "Buddha",
    "Saṅgha"
  ],
  "dn16:4.17.2^speaker": "the Buddha",
  "dn16:4.18.3+dn16:4.18.4^speaker": "Cunda",
  "dn16:4.18.3+dn16:4.18.4^who_else_mentioned": [
    "Cunda",
    "Saṅgha"
  ],
  "dn16:4.18.5^speaker": "Cunda",
  "dn16:4.19.2+dn16:4.19.3^speaker": "the Buddha",
  "dn16:4.19.2+dn16:4.19.3^who_else_mentioned": [
    "Cunda",
    "Māras",
    "Brahmās"
  ],
  "dn16:4.19.4^speaker": "Cunda",
  "dn16:4.20.4^speaker": "the Buddha",
  "dn16:4.20.4^where_else_mentioned": [
    "Kusinārā"
  ],
  "dn16:4.20.4^who_else_mentioned": [
    "Ānanda"
  ],
  "dn16:4.20.5^speaker": "Ānanda",
  "dn16:4.20.13^speaker": "the Buddha",
  "dn16:4.20.13^where_else_mentioned": [
    "Kusinārā"
  ],
  "dn16:4.21.2^speaker": "the Buddha",
  "dn16:4.21.3^speaker": "Ānanda",
  "dn16:4.22.2^geographic_locations_here_and_before": [
    "Bhoganagara",
    "Pāvā",
    "Kusinārā"
  ],
  "dn16:4.22.2^speaker": "the Buddha",
  "dn16:4.22.2^where_here_and_before": [
    "Bhoganagara",
    "Pāvā",
    "Cunda the smith's mango grove",
    "Kusinārā"
  ],
  "dn16:4.22.2^who_around_here_and_before": [
    "the mendicant Saṅgha",
    "Māras",
    "Brahmās",
    "ascetics",
    "brahmins",
    "gods",
    "and humans"
  ],
  "dn16:4.22.2^who_mentioned_here_and_before": [
    ""
  ],
  "dn16:4.22.4+dn16:4.22.6^speaker": "Ānanda",
  "dn16:4.22.4+dn16:4.22.6^where_else_mentioned": [
    "The Kakutthā river"
  ],
  "dn16:4.22.4+dn16:4.22.6^who_else_mentioned": [
    "Buddha"
  ],
  "dn16:4.24.2^speaker": "the Buddha",
  "dn16:4.24.3^speaker": "Ānanda",
  "dn16:4.25.2+dn16:4.25.3^speaker": "Ānanda",
  "dn16:4.25.5+dn16:4.25.7^speaker": "Ānanda",
  "dn16:4.26.4+dn16:4.27.18^speaker": "Pukkusa the Malla",
  "dn16:4.28.1+dn16:4.28.4^speaker": "the Buddha",
  "dn16:4.28.1+dn16:4.28.4^who_else_mentioned": [
    "Pukkusa"
  ],
  "dn16:4.29.1+dn16:4.29.2^speaker": "Pukkusa the Malla",
  "dn16:4.30.1+dn16:4.33.4^speaker": "the Buddha",
  "dn16:4.30.1+dn16:4.33.4^who_else_mentioned": [
    "Pukkusa"
  ],
  "dn16:4.34.2+dn16:4.34.6^speaker": "Pukkusa the Malla",
  "dn16:4.34.2+dn16:4.34.6^where_else_mentioned": [
    "Āḷāra Kālāma"
  ],
  "dn16:4.34.2+dn16:4.34.6^who_else_mentioned": [
    "Buddha",
    "Saṅgha"
  ],
  "dn16:4.35.2^speaker": "Pukkusa the Malla",
  "dn16:4.35.3^speaker": "that man",
  "dn16:4.35.5^speaker": "Pukkusa the Malla",
  "dn16:4.35.6^speaker": "the Buddha",
  "dn16:4.35.7^geographic_locations_here_and_before": [
    "Ātumā"
  ],
  "dn16:4.35.7^speaker": "Pukkusa the Malla",
  "dn16:4.35.7^where_here_and_before": [
    "near Ātumā in a threshing-hut"
  ],
  "dn16:4.35.7^who_around_here_and_before": [
    "Ānanda"
  ],
  "dn16:4.35.7^who_mentioned_here_and_before": [
    "Āḷāra Kālāma"
  ],
  "dn16:4.37.4+dn16:4.37.5^speaker": "Ānanda",
  "dn16:4.37.4+dn16:4.37.5^who_else_mentioned": [
    "Buddha"
  ],
  "dn16:4.37.6+dn16:4.38.5^speaker": "the Buddha",
  "dn16:4.37.6+dn16:4.38.5^where_else_mentioned": [
    "Mallas",
    "Upavattana",
    "Kusinārā",
    "the Kakutthā River"
  ],
  "dn16:4.37.6+dn16:4.38.5^who_else_mentioned": [
    "Ānanda"
  ],
  "dn16:4.38.6^speaker": "Ānanda",
  "dn16:4.39.3^speaker": "the Buddha",
  "dn16:4.39.3^who_else_mentioned": [
    "Cundaka"
  ],
  "dn16:4.40.1^speaker": "Cundaka",
  "dn16:4.41.10^speaker": "the Buddha",
  "dn16:4.42.2+dn16:4.42.13^speaker": "the Buddha",
  "dn16:4.42.2+dn16:4.42.13^who_else_mentioned": [
    "Ānanda",
    "Cunda the smith",
    "Cunda",
    "Buddha"
  ],
  "dn16:4.43.2+dn16:4.43.5^speaker": "the Buddha",
  "dn16:5.1.2^speaker": "the Buddha",
  "dn16:5.1.2^where_else_mentioned": [
    "Ānanda",
    "the Golden River",
    "Mallas",
    "Upavattana",
    "Kusinārā"
  ],
  "dn16:5.1.3^speaker": "Ānanda",
  "dn16:5.1.5^speaker": "the Buddha",
  "dn16:5.1.6^geographic_locations_here_and_before": [
    "Kakudhā",
    "Upavatta",
    "Kusinārā"
  ],
  "dn16:5.1.6^speaker": "Ānanda",
  "dn16:5.1.6^where_here_and_before": [
    "Kakutthā River",
    "mango grove",
    "Golden River",
    "sal forest of the Mallas at Upavattana near Kusinārā"
  ],
  "dn16:5.1.6^who_around_here_and_before": [
    "Pukkusa the Malla",
    "Cundaka"
  ],
  "dn16:5.3.8+dn16:5.3.10^speaker": "the Buddha",
  "dn16:5.4.3^speaker": "the Buddha",
  "dn16:5.4.5+dn16:5.4.8^speaker": "Ānanda",
  "dn16:5.4.5+dn16:5.4.8^who_else_mentioned": [
    "Upavāṇa",
    "Buddha"
  ],
  "dn16:5.5.2+dn16:5.5.5^speaker": "Ānanda",
  "dn16:5.5.2+dn16:5.5.5^who_else_mentioned": [
    "Upavāṇa",
    "Buddha"
  ],
  "dn16:5.5.7+dn16:5.5.13^speaker": "the Buddha",
  "dn16:5.5.7+dn16:5.5.13^who_else_mentioned": [
    "Buddhas",
    "Buddha",
    "the Realized One"
  ],
  "dn16:5.6.1^speaker": "Ānanda",
  "dn16:5.6.2+dn16:5.6.7^speaker": "the Buddha",
  "dn16:5.6.2+dn16:5.6.7^where_else_mentioned": [
    "the Holy One"
  ],
  "dn16:5.6.2+dn16:5.6.7^who_else_mentioned": [
    "Ānanda"
  ],
  "dn16:5.7.1+dn16:5.7.3^speaker": "Ānanda",
  "dn16:5.7.1+dn16:5.7.3^who_else_mentioned": [
    "Buddha"
  ],
  "dn16:5.8.1+dn16:5.8.10^speaker": "the Buddha",
  "dn16:5.8.1+dn16:5.8.10^who_else_mentioned": [
    "Buddha"
  ],
  "dn16:5.9.1^speaker": "Ānanda",
  "dn16:5.9.2^speaker": "the Buddha",
  "dn16:5.9.2^who_else_mentioned": [
    "Ānanda"
  ],
  "dn16:5.9.3^speaker": "Ānanda",
  "dn16:5.9.4^speaker": "the Buddha",
  "dn16:5.9.4^who_else_mentioned": [
    "Ānanda"
  ],
  "dn16:5.9.5^speaker": "Ānanda",
  "dn16:5.9.6^speaker": "the Buddha",
  "dn16:5.10.1^speaker": "Ānanda",
  "dn16:5.10.2+dn16:5.10.4^speaker": "the Buddha",
  "dn16:5.10.2+dn16:5.10.4^who_else_mentioned": [
    "Ānanda"
  ],
  "dn16:5.11.1^speaker": "Ānanda",
  "dn16:5.11.2^speaker": "the Buddha",
  "dn16:5.11.3^speaker": "Ānanda",
  "dn16:5.11.3^where_here_and_before": [
    "the sky"
  ],
  "dn16:5.11.3^who_around_here_and_before": [
    "Upavāṇa"
  ],
  "dn16:5.11.3^who_mentioned_here_and_before": [
    "",
    "astute aristocrats",
    "brahmins",
    "and householders"
  ],
  "dn16:5.11.4+dn16:5.12.20^speaker": "the Buddha",
  "dn16:5.11.4+dn16:5.12.20^who_else_mentioned": [
    "Buddha"
  ],
  "dn16:5.13.2^speaker": "Ānanda",
  "dn16:5.13.4^speaker": "the Buddha",
  "dn16:5.13.5+dn16:5.13.6^speaker": "the Buddha",
  "dn16:5.13.5+dn16:5.13.6^who_else_mentioned": [
    "Ānanda"
  ],
  "dn16:5.13.8+dn16:5.13.9^speaker": "the Buddha",
  "dn16:5.13.10^speaker": "the monk",
  "dn16:5.13.11^speaker": "the monk",
  "dn16:5.13.11^who_else_mentioned": [
    "Ānanda"
  ],
  "dn16:5.14.1^speaker": "Ānanda",
  "dn16:5.14.2+dn16:5.14.6^speaker": "the Buddha",
  "dn16:5.15.2+dn16:5.16.26^speaker": "the Buddha",
  "dn16:5.15.2+dn16:5.16.26^who_else_mentioned": [
    "Buddhas"
  ],
  "dn16:5.17.2+dn16:5.17.7^speaker": "Ānanda",
  "dn16:5.17.2+dn16:5.17.7^where_else_mentioned": [
    "Campā",
    "Rājagaha",
    "Benares"
  ],
  "dn16:5.17.2+dn16:5.17.7^who_else_mentioned": [
    "Sāvatthī",
    "Sāketa",
    "Kosambī",
    "Buddha"
  ],
  "dn16:5.17.8+dn16:5.19.5^speaker": "the Buddha",
  "dn16:5.17.8+dn16:5.19.5^where_else_mentioned": [
    "Kusinārā"
  ],
  "dn16:5.17.8+dn16:5.19.5^who_else_mentioned": [
    "Mahāsudassana",
    "Kusāvatī",
    "Ānanda",
    "Mallas",
    "Vāseṭṭhas"
  ],
  "dn16:5.19.6^speaker": "Ānanda",
  "dn16:5.20.3+dn16:5.20.6^speaker": "Ānanda",
  "dn16:5.20.3+dn16:5.20.6^who_else_mentioned": [
    "Vāseṭ",
    "Vāseṭṭhas"
  ],
  "dn16:5.21.2^speaker": "the Mallas, their sons, daughters-in-law, and wives",
  "dn16:5.21.2^where_else_mentioned": [
    "the Holy One"
  ],
  "dn16:5.22.2+dn16:5.22.4^speaker": "Ānanda",
  "dn16:5.22.2+dn16:5.22.4^who_else_mentioned": [
    "Mallas",
    "Buddha",
    "Malla"
  ],
  "dn16:5.22.2^geographic_locations_here_and_before": [
    "Kusinārā",
    "Upavatta"
  ],
  "dn16:5.22.2^where_here_and_before": [
    "Kusinārā",
    "Upavattana"
  ],
  "dn16:5.22.2^who_around_here_and_before": [
    "the monk",
    "the Mallas",
    "their sons",
    "daughters-in-law",
    "and wives",
    "Subhadda"
  ],
  "dn16:5.22.2^who_mentioned_here_and_before": [
    "Vāseṭṭhas"
  ],
  "dn16:5.23.5+dn16:5.23.9^speaker": "Subhadda",
  "dn16:5.23.5+dn16:5.23.9^where_else_mentioned": [
    "Gotama"
  ],
  "dn16:5.23.5+dn16:5.23.9^who_else_mentioned": [
    "Buddhas",
    "Buddha"
  ],
  "dn16:5.24.2+dn16:5.24.7^speaker": "Subhadda",
  "dn16:5.24.2+dn16:5.24.7^where_else_mentioned": [
    "Gotama"
  ],
  "dn16:5.24.2+dn16:5.24.7^who_else_mentioned": [
    "Ānanda",
    "Buddhas",
    "Buddha"
  ],
  "dn16:5.24.9^speaker": "Ānanda",
  "dn16:5.24.9^who_else_mentioned": [
    "Subhadda"
  ],
  "dn16:5.25.3+dn16:5.25.5^speaker": "the Buddha",
  "dn16:5.25.3+dn16:5.25.5^who_else_mentioned": [
    "Ānanda",
    "Subhadda"
  ],
  "dn16:5.25.7^speaker": "Ānanda",
  "dn16:5.25.7^who_else_mentioned": [
    "Subhadda",
    "Buddha"
  ],
  "dn16:5.26.2+dn16:5.26.4^speaker": "Subhadda",
  "dn16:5.26.2+dn16:5.26.4^who_else_mentioned": [
    "Gotama",
    "Pūraṇa Kassapa",
    "Makkhali Gosāla",
    "Nigaṇṭha Nāṭaputta",
    "Sañjaya Belaṭṭhiputta",
    "Pakudha Kaccāyana",
    "Ajita Kesakambala"
  ],
  "dn16:5.26.5+dn16:5.26.8^speaker": "the Buddha",
  "dn16:5.26.5+dn16:5.26.8^who_else_mentioned": [
    "Subhadda"
  ],
  "dn16:5.26.9^speaker": "Subhadda",
  "dn16:5.27.1+dn16:5.27.15^speaker": "the Buddha",
  "dn16:5.27.1+dn16:5.27.15^who_else_mentioned": [
    "Subaddha"
  ],
  "dn16:5.28.2+dn16:5.28.5^speaker": "Subhadda",
  "dn16:5.28.2+dn16:5.28.5^who_else_mentioned": [
    "Buddha",
    "Saṅgha"
  ],
  "dn16:5.29.1+dn16:5.29.2^speaker": "the Buddha",
  "dn16:5.29.1+dn16:5.29.2^who_else_mentioned": [
    "Subhadda"
  ],
  "dn16:5.29.3^speaker": "Subhadda",
  "dn16:5.29.5^speaker": "the Buddha",
  "dn16:5.29.5^who_else_mentioned": [
    "Ānanda",
    "Subhadda"
  ],
  "dn16:5.29.6^speaker": "Ānanda",
  "dn16:5.30.2+dn16:5.30.3^speaker": "Subhadda",
  "dn16:5.30.2+dn16:5.30.3^who_else_mentioned": [
    "Reverand"
  ],
  "dn16:5.30.6^geographic_locations_here_and_before": [
    "Upavatta",
    "Kusinārā"
  ],
  "dn16:5.30.6^speaker": "Subhadda",
  "dn16:5.30.6^where_here_and_before": [
    "Mallian sal grove at Upavattana",
    "Kusinārā"
  ],
  "dn16:5.30.6^who_around_here_and_before": [
    "Ānanda"
  ],
  "dn16:5.30.6^who_mentioned_here_and_before": [
    "brahmins of the past"
  ],
  "dn16:6.1.2+dn16:6.4.1^speaker": "the Buddha",
  "dn16:6.1.2+dn16:6.4.1^who_else_mentioned": [
    "Ānanda",
    "Channa"
  ],
  "dn16:6.4.2^speaker": "Ānanda",
  "dn16:6.4.3+dn16:6.4.4^speaker": "the Buddha",
  "dn16:6.4.3+dn16:6.4.4^who_else_mentioned": [
    "Channa"
  ],
  "dn16:6.5.2+dn16:6.5.3^speaker": "the Buddha",
  "dn16:6.5.2+dn16:6.5.3^who_else_mentioned": [
    "Buddha",
    "Saṅgha"
  ],
  "dn16:6.6.3+dn16:6.6.4^speaker": "the Buddha",
  "dn16:6.6.3+dn16:6.6.4^who_else_mentioned": [
    "Buddha",
    "Saṅgha"
  ],
  "dn16:6.6.7^speaker": "the Buddha",
  "dn16:6.6.10^speaker": "Ānanda",
  "dn16:6.6.10^who_else_mentioned": [
    "Saṅgha",
    "Buddha"
  ],
  "dn16:6.6.11+dn16:6.6.12^speaker": "the Buddha",
  "dn16:6.6.11+dn16:6.6.12^who_else_mentioned": [
    "Saṅgha",
    "Buddha"
  ],
  "dn16:6.7.2+dn16:6.7.3^speaker": "the Buddha",
  "dn16:6.8.3^speaker": "Ānanda",
  "dn16:6.8.3^who_else_mentioned": [
    "Anuruddha",
    "Buddha"
  ],
  "dn16:6.8.4^speaker": "Anuruddha",
  "dn16:6.8.4^who_else_mentioned": [
    "Ānanda"
  ],
  "dn16:6.10.3+dn16:6.10.8^speaker": "Brahmā Sahampati",
  "dn16:6.10.3+dn16:6.10.8^who_else_mentioned": [
    "Buddha"
  ],
  "dn16:6.10.10+dn16:6.10.13^speaker": "Sakka",
  "dn16:6.10.10^where_here_and_before": [
    "the Buddha's presence"
  ],
  "dn16:6.10.10^who_around_here_and_before": [
    "Subhadda",
    "Ānanda",
    "Anuruddha"
  ],
  "dn16:6.10.10^who_mentioned_here_and_before": [
    "Channa"
  ],
  "dn16:6.10.15+dn16:6.10.22^speaker": "Anuruddha",
  "dn16:6.10.24+dn16:6.10.27^speaker": "Ānanda",
  "dn16:6.10.24+dn16:6.10.27^who_else_mentioned": [
    "Buddha"
  ],
  "dn16:6.10.28^speaker": "the mendicants",
  "dn16:6.10.28^where_else_mentioned": [
    "the Holy One"
  ],
  "dn16:6.10.30^speaker": "the mendicants who were free of desire",
  "dn16:6.11.2+dn16:6.11.6^speaker": "Anuruddha",
  "dn16:6.11.2+dn16:6.11.6^who_else_mentioned": [
    "Buddha"
  ],
  "dn16:6.11.7^speaker": "Ānanda",
  "dn16:6.11.8+dn16:6.11.13^speaker": "Anuruddha",
  "dn16:6.11.8+dn16:6.11.13^where_else_mentioned": [
    "the Holy One"
  ],
  "dn16:6.11.8+dn16:6.11.13^who_else_mentioned": [
    "Ānanda"
  ],
  "dn16:6.12.2+dn16:6.12.4^speaker": "Anuruddha",
  "dn16:6.12.2+dn16:6.12.4^where_else_mentioned": [
    "Kusinārā"
  ],
  "dn16:6.12.2+dn16:6.12.4^who_else_mentioned": [
    "Ānanda",
    "Mallas",
    "Vāseṭ",
    "Buddha"
  ],
  "dn16:6.12.5^speaker": "Ānanda",
  "dn16:6.12.8+dn16:6.12.9^speaker": "Ānanda",
  "dn16:6.12.8+dn16:6.12.9^who_else_mentioned": [
    "Buddha"
  ],
  "dn16:6.12.11^speaker": "the Mallas, their sons, daughters-in-law, and wives",
  "dn16:6.12.11^where_else_mentioned": [
    "the Holy One"
  ],
  "dn16:6.13.2^speaker": "the Mallas",
  "dn16:6.13.2^where_else_mentioned": [
    "Kusinārā"
  ],
  "dn16:6.13.5^speaker": "the Mallas",
  "dn16:6.13.5^who_else_mentioned": [
    "Buddha"
  ],
  "dn16:6.14.2^speaker": "the Mallas",
  "dn16:6.14.2^who_else_mentioned": [
    "Buddha"
  ],
  "dn16:6.14.4^speaker": "eight of the leading Mallas",
  "dn16:6.14.4^who_else_mentioned": [
    "Buddha"
  ],
  "dn16:6.14.6^speaker": "the Mallas",
  "dn16:6.14.6^who_else_mentioned": [
    "Anuruddha",
    "Mallian",
    "Buddha"
  ],
  "dn16:6.14.8^speaker": "Anuruddha",
  "dn16:6.15.1^geographic_locations_here_and_before": [
    "Upavatta",
    "Kusinārā"
  ],
  "dn16:6.15.1^speaker": "the Mallas",
  "dn16:6.15.1^where_here_and_before": [
    "Upavattana",
    "Kusinārā"
  ],
  "dn16:6.15.1^who_around_here_and_before": [
    "Ānanda",
    "Anuruddha",
    "the mendicants",
    "the Mallas",
    "their sons",
    "daughters-in-law",
    "and wives",
    "eight of the leading Mallas"
  ],
  "dn16:6.15.1^who_mentioned_here_and_before": [
    "Brahmā Sahampati",
    "Sakka",
    "lord of gods",
    "Dhamma",
    "deities"
  ],
  "dn16:6.15.2+dn16:6.15.5^speaker": "Anuruddha",
  "dn16:6.15.2+dn16:6.15.5^where_else_mentioned": [
    "Mallian"
  ],
  "dn16:6.15.2+dn16:6.15.5^who_else_mentioned": [
    "Buddha",
    "Makuṭabandhana"
  ],
  "dn16:6.15.6^speaker": "the Mallas",
  "dn16:6.17.2^speaker": "the Mallas",
  "dn16:6.17.3^speaker": "Anuruddha",
  "dn16:6.17.4^speaker": "the Mallas",
  "dn16:6.17.5+dn16:6.17.11^speaker": "Anuruddha",
  "dn16:6.18.2^speaker": "the Mallas",
  "dn16:6.19.5^speaker": "Mahākassapa",
  "dn16:6.19.6+dn16:6.19.7^speaker": "the Ājīvaka ascetic",
  "dn16:6.19.6+dn16:6.19.7^where_else_mentioned": [
    "Gotama"
  ],
  "dn16:6.19.9^speaker": "the mendicants",
  "dn16:6.19.9^where_else_mentioned": [
    "the Holy One"
  ],
  "dn16:6.19.11^speaker": "the mendicants",
  "dn16:6.20.3+dn16:6.20.5^speaker": "Subhadda",
  "dn16:6.20.7+dn16:6.20.10^speaker": "Mahākassapa",
  "dn16:6.20.7+dn16:6.20.10^who_else_mentioned": [
    "Buddha"
  ],
  "dn16:6.21.2^geographic_locations_here_and_before": [
    "Kusinārā"
  ],
  "dn16:6.21.2^speaker": "the Mallas",
  "dn16:6.21.2^where_here_and_before": [
    "Kusinārā"
  ],
  "dn16:6.21.2^who_around_here_and_before": [
    "Mahākassapa",
    "the Ājīvaka ascetic",
    "Subhadda",
    "the mendicants"
  ],
  "dn16:6.21.2^who_else_mentioned": [
    "Buddha"
  ],
  "dn16:6.21.2^who_mentioned_here_and_before": [
    "the deities"
  ],
  "dn16:6.21.4^speaker": "the Mallas",
  "dn16:6.21.4^who_else_mentioned": [
    "Anuruddha",
    "Mallian",
    "Buddha"
  ],
  "dn16:6.21.6^speaker": "Anuruddha",
  "dn16:6.21.6^who_else_mentioned": [
    "Vāseṭ"
  ],
  "dn16:6.21.7^speaker": "the Mallas",
  "dn16:6.21.8+dn16:6.21.10^speaker": "Anuruddha",
  "dn16:6.21.8+dn16:6.21.10^where_else_mentioned": [
    "Pāvā",
    "Kusinārā",
    "Saṅgha"
  ],
  "dn16:6.21.8+dn16:6.21.10^who_else_mentioned": [
    "Mahākassapa",
    "Buddha"
  ],
  "dn16:6.21.11^speaker": "the Mallas",
  "dn16:6.24.4^speaker": "King Ajātasattu of Magadha",
  "dn16:6.24.4^who_else_mentioned": [
    "Buddha"
  ],
  "dn16:6.24.8^speaker": "the Licchavis of Vesālī",
  "dn16:6.24.8^who_else_mentioned": [
    "Buddha"
  ],
  "dn16:6.24.12^speaker": "the Sakyans of Kapilavatthu",
  "dn16:6.24.12^who_else_mentioned": [
    "Buddha"
  ],
  "dn16:6.24.16^speaker": "the Bulas of Allakappa",
  "dn16:6.24.16^who_else_mentioned": [
    "Buddha"
  ],
  "dn16:6.24.20^speaker": "the Koḷiyans of Rāmagāma",
  "dn16:6.24.20^who_else_mentioned": [
    "Buddha"
  ],
  "dn16:6.24.24^geographic_locations_here_and_before": [
    "Kusinārā"
  ],
  "dn16:6.24.24^speaker": "the brahmin of Veṭhadīpa",
  "dn16:6.24.24^where_here_and_before": [
    "Kusinārā"
  ],
  "dn16:6.24.24^who_around_here_and_before": [
    "Mahākassapa",
    "five hundred mendicants"
  ],
  "dn16:6.24.24^who_else_mentioned": [
    "Buddha"
  ],
  "dn16:6.24.24^who_mentioned_here_and_before": [
    "the Buddha"
  ],
  "dn16:6.24.28^speaker": "the Mallas of Pāvā",
  "dn16:6.24.28^who_else_mentioned": [
    "Buddha"
  ],
  "dn16:6.25.2^speaker": "the Mallas of Kusinārā",
  "dn16:6.25.2^who_else_mentioned": [
    "Buddha"
  ],
  "dn16:6.25.4+dn16:6.25.11^speaker": "Doṇa the brahmin",
  "dn16:6.25.4+dn16:6.25.11^who_else_mentioned": [
    "Buddha",
    "Seer"
  ],
  "dn16:6.25.12^speaker": "the Mallas of Kusinārā",
  "dn16:6.25.12^who_else_mentioned": [
    "Buddha"
  ],
  "dn16:6.25.13^speaker": "Doṇa",
  "dn16:6.25.14^speaker": "the Mallas of Kusinārā",
  "dn16:6.26.4^speaker": "the Moras of Pippalivana",
  "dn16:6.26.4^who_else_mentioned": [
    "Buddha"
  ],
  "dn16:6.26.5+dn16:6.26.6^speaker": "the Mallas of Kusinārā",
  "dn16:6.26.5+dn16:6.26.6^who_else_mentioned": [
    "Buddha"
  ],
  "dn16:6.26.5^geographic_locations_here_and_before": [
    "Kusinārā"
  ],
  "dn16:6.26.5^where_here_and_before": [
    "Kusinārā"
  ],
  "dn16:6.26.5^who_around_here_and_before": [
    "King Ajātasattu of Magadha",
    "the Licchavis of Vesālī",
    "the Sakyans of Kapilavatthu",
    "the Bulas of Allakappa",
    "the Koḷiyans of Rāmagāma",
    "the brahmin of Veṭhadīpa",
    "the Mallas of Pāvā",
    "the Mallas of Kusinārā",
    "the brahmin Doṇa",
    "and the Moriyas of Pippalivana"
  ],
  "dn16:6.26.5^who_mentioned_here_and_before": [
    "the gods of the Three and Thirty",
    "the city of Gandhāra",
    "the realm of the Kaliṅga King",
    "and a dragon king"
  ],
  "dn16^initial_geographic_location": [
    "Rājagaha",
    "Gijjhakūṭa"
  ],
  "dn16^where": "Rājagaha, on the Vulture's Peak Mountain"
}