{
  "_comment": "This data is an early work-in-progress and contains errors. Produced by @michaelh at Discuss and Discover SuttaCentral forum - please get in touch! Finished code forthcoming.",
  "sn20.9:1.5": "the mendicants",
  "sn20.9:1.7": "the junior mendicant",
  "sn20.9:3.1": "the Buddha",
  "sn20.9:3.2": "the Buddha",
  "sn20.9:3.3": "the Buddha",
  "sn20.9:3.4": "the Buddha",
  "sn20.9:3.5": "the Buddha",
  "sn20.9:3.6": "the Buddha",
  "sn20.9:4.1": "the Buddha",
  "sn20.9:4.2": "the Buddha",
  "sn20.9:4.3": "the Buddha",
  "sn20.9:4.4": "the Buddha",
  "sn20.9:4.5": "the Buddha",
  "sn20.9:4.6": "the Buddha",
  "sn20.9:4.7": "the Buddha",
  "sn20.9:4.8": "the Buddha",
  "sn20.9:4.9": "the Buddha",
  "sn20.9:4.10": "the Buddha",
  "sn20.9:4.11": "the Buddha",
  "sn20.9:4.12": "the Buddha",
  "sn20.9:4.13": "the Buddha"
}