{
  "sn36.7:2.1": "the Buddha (assumed)",
  "sn36.7:2.2": "the Buddha (assumed)",
  "sn36.7:3.1": "the Buddha (assumed)",
  "sn36.7:3.2": "the Buddha (assumed)",
  "sn36.7:3.3": "the Buddha (assumed)",
  "sn36.7:3.4": "the Buddha (assumed)",
  "sn36.7:3.5": "the Buddha (assumed)",
  "sn36.7:3.6": "the Buddha (assumed)",
  "sn36.7:4.1": "the Buddha (assumed)",
  "sn36.7:4.2": "the Buddha (assumed)",
  "sn36.7:4.3": "the Buddha (assumed)",
  "sn36.7:4.4": "the Buddha (assumed)",
  "sn36.7:4.5": "the Buddha (assumed)",
  "sn36.7:5.1": "the Buddha (assumed)",
  "sn36.7:5.2": "the Buddha (assumed)",
  "sn36.7:5.3": "the Buddha (assumed)",
  "sn36.7:5.4": "the Buddha (assumed)",
  "sn36.7:5.5": "the Buddha (assumed)",
  "sn36.7:5.6": "the Buddha (assumed)",
  "sn36.7:5.7": "the Buddha (assumed)",
  "sn36.7:5.8": "the Buddha (assumed)",
  "sn36.7:5.9": "the Buddha (assumed)",
  "sn36.7:6.1": "the Buddha (assumed)",
  "sn36.7:6.3": "the Buddha (assumed)",
  "sn36.7:6.4": "the Buddha (assumed)",
  "sn36.7:6.5": "the Buddha (assumed)",
  "sn36.7:6.6": "the Buddha (assumed)",
  "sn36.7:6.7": "the Buddha (assumed)",
  "sn36.7:6.8": "the Buddha (assumed)",
  "sn36.7:6.9": "the Buddha (assumed)",
  "sn36.7:6.10": "the Buddha (assumed)",
  "sn36.7:7.1": "the Buddha (assumed)",
  "sn36.7:7.2": "the Buddha (assumed)",
  "sn36.7:7.3": "the Buddha (assumed)",
  "sn36.7:7.4": "the Buddha (assumed)",
  "sn36.7:7.5": "the Buddha (assumed)",
  "sn36.7:7.6": "the Buddha (assumed)",
  "sn36.7:7.7": "the Buddha (assumed)",
  "sn36.7:7.8": "the Buddha (assumed)",
  "sn36.7:7.9": "the Buddha (assumed)",
  "sn36.7:8.1": "the Buddha (assumed)",
  "sn36.7:8.2": "the Buddha (assumed)",
  "sn36.7:8.3": "the Buddha (assumed)",
  "sn36.7:8.4": "the Buddha (assumed)",
  "sn36.7:8.5": "the Buddha (assumed)",
  "sn36.7:8.6": "the Buddha (assumed)",
  "sn36.7:8.7": "the Buddha (assumed)",
  "sn36.7:8.8": "the Buddha (assumed)",
  "sn36.7:9.1": "the Buddha (assumed)",
  "sn36.7:9.2": "the Buddha (assumed)",
  "sn36.7:9.3": "the Buddha (assumed)",
  "sn36.7:9.4": "the Buddha (assumed)"
}