{
  "_comment": "This data is an early work-in-progress and contains errors. Keys with _else are produced with non-trained Stanford NLP and as such only includes capitalized words. The + designates a segment range. Produced by @michaelh at Discuss and Discover SuttaCentral forum - please get in touch! Finished code forthcoming.",
  "mn55:3.1+mn55:3.3^speaker": "Jīvaka",
  "mn55:3.1+mn55:3.3^who_else_mentioned": [
    "Gotama",
    "Buddha"
  ],
  "mn55:4.1+mn55:6.13^speaker": "the Buddha",
  "mn55:4.1+mn55:6.13^who_else_mentioned": [
    "Jīvaka"
  ],
  "mn55:6.14^speaker": "Jīvaka",
  "mn55:6.15^speaker": "the Buddha",
  "mn55:7.1+mn55:7.5^speaker": "the Buddha",
  "mn55:7.1+mn55:7.5^who_else_mentioned": [
    "Brahmā",
    "Buddha"
  ],
  "mn55:7.6+mn55:7.7^speaker": "Jīvaka",
  "mn55:7.8^speaker": "Jīvaka",
  "mn55:8-10.1+mn55:8-10.16^speaker": "the Buddha",
  "mn55:8-10.1+mn55:8-10.16^who_else_mentioned": [
    "Jīvaka"
  ],
  "mn55:8-10.17^speaker": "Jīvaka",
  "mn55:8-10.18^speaker": "the Buddha",
  "mn55:11.1+mn55:11.5^speaker": "the Buddha",
  "mn55:11.1+mn55:11.5^who_else_mentioned": [
    "Brahmā",
    "Buddha"
  ],
  "mn55:11.6+mn55:11.7^speaker": "Jīvaka",
  "mn55:11.8^speaker": "Jīvaka",
  "mn55:12.1+mn55:12.9^speaker": "the Buddha",
  "mn55:12.1+mn55:12.9^who_else_mentioned": [
    "Jīvaka"
  ],
  "mn55:13.2+mn55:13.6^speaker": "Jīvaka",
  "mn55:13.2+mn55:13.6^who_else_mentioned": [
    "Buddha"
  ],
  "mn55:13.2^geographic_locations_here_and_before": [
    "Rājagaha"
  ],
  "mn55:13.2^where_here_and_before": [
    "Rājagaha in the Mango Grove of Jīvaka Komārabhacca"
  ],
  "mn55^initial_geographic_location": [
    "Rājagaha"
  ],
  "mn55^where": "Rājagaha in the Mango Grove of Jīvaka Komārabhacca"
}