{
  "_comment": "This data is an early work-in-progress and contains errors. Keys with _else are produced with non-trained Stanford NLP and as such only includes capitalized words. The + designates a segment range. Produced by @michaelh at Discuss and Discover SuttaCentral forum - please get in touch! Finished code forthcoming.",
  "dn24:1.1.5+dn24:1.1.6^where_else_mentioned": "Anupiya",
  "dn24:1.1.5+dn24:1.1.6^who_else_mentioned": "Bhaggavagotta",
  "dn24:1.2.10+dn24:1.2.13^who_else_mentioned": "Sunakkhatta, Licchavi, Bhaggava, Buddha",
  "dn24:1.2.14+dn24:2.21.8^where_else_mentioned": "Th\u016blus, Ves\u0101l\u012b, Gotamaka, Sattamba, Bahuputta",
  "dn24:1.2.14+dn24:2.21.8^who_else_mentioned": "Bhaggava, Sunakkhatta, Licchavi, Buddha, Vajjian, Sa\u1e45gha, Gotama, Uttarak\u0101, Korakkhattiya, Sakyan, K\u0101laka\u00f1jas, Ka\u1e37\u0101rama\u1e6d\u1e6daka, P\u0101\u1e6dikaputta, Ajita, Licchavis, P\u0101\u1e6dika, J\u0101liya, the Holy One, P\u0101\u1e6dikaputtas, Buddhas, Brahm\u0101, the Universal Seer, the Wielder of Power",
  "dn24:1.1.5+dn24:1.1.6": "The Buddha",
  "dn24:1.2.3+dn24:1.2.6": "The wanderer Bhaggavagotta",
  "dn24:1.2.10+dn24:1.2.13": "Sunakkhatta the Licchavi",
  "dn24:1.3.6": "Sunakkhatta the Licchavi",
  "dn24:1.3.9": "The Buddha",
  "dn24:1.4.3": "Sunakkhatta the Licchavi",
  "dn24:1.4.6": "The Buddha",
  "dn24:1.5.3": "Sunakkhatta the Licchavi",
  "dn24:1.5.6": "The Buddha",
  "dn24:1.6.2": "Sunakkhatta the Licchavi",
  "dn24:1.6.5": "The Buddha",
  "dn24:1.6.8": "The Buddha",
  "dn24:1.7.12": "Sunakkhatta the Licchavi",
  "dn24:1.10.9": "Sunakkhatta the Licchavi",
  "dn24:1.14.11": "The Buddha",
  "dn24:1.21.13": "The naked ascetic P\u0101\u1e6dikaputta",
  "dn24:1.22.6": "The naked ascetic P\u0101\u1e6dikaputta",
  "dn24:2.2.4": "The naked ascetic P\u0101\u1e6dikaputta",
  "dn24:2.3.10": "The naked ascetic P\u0101\u1e6dikaputta",
  "dn24:2.5.4": "The naked ascetic P\u0101\u1e6dikaputta",
  "dn24:2.8.4": "The jackal",
  "dn24:2.10.6": "The jackal",
  "dn24:2.11.3": "The naked ascetic P\u0101\u1e6dikaputta",
  "dn24:2.12.6": "The naked ascetic P\u0101\u1e6dikaputta",
  "dn24:2.13.10": "The Buddha",
  "dn24:2.16.2": "Brahm\u0101",
  "dn24:2.18.9": "Brahm\u0101",
  "dn24:2.19.9": "Brahm\u0101",
  "dn24:2.20.9": "Brahm\u0101",
  "dn24:2.21.4": "The Buddha",
  "dn24:1.2.14+dn24:2.21.8": "",
  "dn24:2.21.9+dn24:2.21.10^who_else_mentioned": "Buddha",
  "dn24:2.21.11+dn24:2.21.12^who_else_mentioned": "Bhaggava",
  "dn24:2.21.13+dn24:2.21.14^who_else_mentioned": "Buddha",
  "dn24:2.21.9+dn24:2.21.10": "Bhaggava",
  "dn24:2.21.11+dn24:2.21.12": "The Buddha",
  "dn24:2.21.13+dn24:2.21.14": "Bhaggavagotta",
  "where": "the Mallian town named Anupiya"
}