{
  "_comment": "This data is an early work-in-progress and contains errors. Keys with _else are produced with non-trained Stanford NLP and as such only includes capitalized words. The + designates a segment range. Produced by @michaelh at Discuss and Discover SuttaCentral forum - please get in touch! Finished code forthcoming.",
  "sn22.126:1.3+sn22.126:1.5": "a mendicant",
  "sn22.126:2.1+sn22.126:2.15": "the Buddha",
  "sn22.126:3.2+sn22.126:3.4": "a mendicant",
  "sn22.126:4.1+sn22.126:4.15": "the Buddha",
  "before^sn22.126:4.1^where": "S\u0101vatth\u012b",
  "where": "S\u0101vatth\u012b"
}