{
  "_comment": "This data is an early work-in-progress and contains errors. Keys with _else are produced with non-trained Stanford NLP and as such only includes capitalized words. The + designates a segment range. Produced by @michaelh at Discuss and Discover SuttaCentral forum - please get in touch! Finished code forthcoming.",
  "sn45.19:1.4+sn45.19:1.8^who_else_mentioned": "Bhadda",
  "sn45.19:1.2+sn45.19:1.3": "Reverend Bhadda",
  "sn45.19:1.4+sn45.19:1.8": "the Buddha (assumed)",
  "sn45.19:1.7": "Reverend Bhadda",
  "sn45.19:1.9": "the Buddha (assumed)",
  "sn45.19:1.10+sn45.19:1.13": "the Buddha (assumed)",
  "before^sn45.19:1.10^where": "P\u0101\u1e6daliputta",
  "where": "P\u0101\u1e6daliputta"
}