{
  "an3.91:1.6": "Kassapagotta",
  "an3.91:2.2": "Kassapagotta",
  "an3.91:2.3": "Kassapagotta",
  "an3.91:2.4": "Kassapagotta",
  "an3.91:2.5": "Kassapagotta",
  "an3.91:3.11": "Kassapagotta",
  "an3.91:3.12": "Kassapagotta",
  "an3.91:3.13": "Kassapagotta",
  "an3.91:4.1": "the Buddha",
  "an3.91:4.3": "the Buddha",
  "an3.91:4.4": "the Buddha",
  "an3.91:5.1": "the Buddha",
  "an3.91:5.2": "the Buddha",
  "an3.91:5.3": "the Buddha",
  "an3.91:5.4": "the Buddha",
  "an3.91:6.1": "the Buddha",
  "an3.91:6.2": "the Buddha",
  "an3.91:6.5": "the Buddha",
  "an3.91:7.1": "the Buddha",
  "an3.91:7.2": "the Buddha",
  "an3.91:7.3": "the Buddha",
  "an3.91:7.4": "the Buddha",
  "an3.91:8.1": "the Buddha",
  "an3.91:8.2": "the Buddha",
  "an3.91:8.5": "the Buddha"
}