{
  "sn22.86:1.5": "Wanderers who follow other paths",
  "sn22.86:1.6": "Wanderers who follow other paths",
  "sn22.86:2.2": "Anurādha",
  "sn22.86:2.3": "Anurādha",
  "sn22.86:2.5": "Wanderers who follow other paths",
  "sn22.86:2.6": "Wanderers who follow other paths",
  "sn22.86:3.2": "Anurādha",
  "sn22.86:3.3": "Anurādha",
  "sn22.86:7.1": "the Buddha",
  "sn22.86:7.2": "the Buddha",
  "sn22.86:7.3": "Anurādha",
  "sn22.86:7.4": "the Buddha",
  "sn22.86:7.5": "Anurādha",
  "sn22.86:7.6": "the Buddha",
  "sn22.86:7.7": "the Buddha",
  "sn22.86:7.8": "Anurādha",
  "sn22.86:7.9": "the Buddha",
  "sn22.86:7.10": "the Buddha",
  "sn22.86:7.11": "the Buddha",
  "sn22.86:7.12": "the Buddha",
  "sn22.86:7.13": "Anurādha",
  "sn22.86:7.14": "the Buddha",
  "sn22.86:7.15": "the Buddha",
  "sn22.86:7.16": "the Buddha",
  "sn22.86:8.1": "the Buddha",
  "sn22.86:8.2": "the Buddha",
  "sn22.86:8.3": "Anurādha",
  "sn22.86:8.4": "the Buddha",
  "sn22.86:8.5": "the Buddha",
  "sn22.86:8.6": "the Buddha",
  "sn22.86:8.7": "the Buddha",
  "sn22.86:8.8": "Anurādha",
  "sn22.86:9.1": "the Buddha",
  "sn22.86:9.2": "the Buddha",
  "sn22.86:9.3": "Anurādha",
  "sn22.86:9.4": "the Buddha",
  "sn22.86:9.5": "Anurādha",
  "sn22.86:9.6": "the Buddha",
  "sn22.86:9.7": "the Buddha",
  "sn22.86:9.8": "the Buddha",
  "sn22.86:9.9": "the Buddha",
  "sn22.86:9.10": "the Buddha",
  "sn22.86:9.11": "the Buddha",
  "sn22.86:9.12": "the Buddha",
  "sn22.86:9.13": "the Buddha",
  "sn22.86:9.14": "Anurādha",
  "sn22.86:10.1": "the Buddha",
  "sn22.86:10.2": "the Buddha",
  "sn22.86:10.3": "Anurādha",
  "sn22.86:11.1": "the Buddha",
  "sn22.86:11.2": "the Buddha",
  "sn22.86:11.3": "Anurādha",
  "sn22.86:12.1": "the Buddha",
  "sn22.86:12.2": "the Buddha",
  "sn22.86:12.3": "the Buddha",
  "sn22.86:12.4": "Anurādha",
  "sn22.86:13.1": "the Buddha",
  "sn22.86:13.2": "the Buddha"
}