{
  "sn35.43:1.3": "the Buddha (assumed)",
  "sn35.43:1.4": "the Buddha (assumed)",
  "sn35.43:1.5": "the Buddha (assumed)",
  "sn35.43:1.6": "the Buddha (assumed)",
  "sn35.43:1.7": "the Buddha (assumed)",
  "sn35.43:1.9": "the Buddha (assumed)",
  "sn35.43:1.10": "the Buddha (assumed)",
  "sn35.43:1.11": "the Buddha (assumed)",
  "sn35.43:1.12": "the Buddha (assumed)",
  "sn35.43:1.17": "the Buddha (assumed)",
  "sn35.44:1.1": "the Buddha (assumed)",
  "sn35.45:1.1": "the Buddha (assumed)",
  "sn35.46:1.1": "the Buddha (assumed)",
  "sn35.47:1.1": "the Buddha (assumed)",
  "sn35.48:1.1": "the Buddha (assumed)",
  "sn35.49:1.1": "the Buddha (assumed)",
  "sn35.50:1.1": "the Buddha (assumed)",
  "sn35.51:1.1": "the Buddha (assumed)"
}